_examples/test_mysql_create_table.py
_examples/test_psql.py
_examples/_tests/test1.py
_examples/_tests/test2.py
_private/ff.py
_private/case/crawl_csdn.py
_private/case/pool-wait.py
_private/demo/crawl_csdn.py
_private/test/新的线程池管理.py
_private/test/测试 - PoolWait、PoolMan.py
_private/test/测试 - 控制日志输出等级.py
_private/test/测试-类型检查装饰器.py
_private/test/测试v1v2线程池.py
_private/test/识别字符串是否为英文.py
_private/爬虫面试题/天下药仓/pdd.py
_private/爬虫面试题/天下药仓/pdd2.py
_private/爬虫面试题/紫嫣喷雾/NSTL.py
_private/爬虫面试题/紫嫣喷雾/NSTL2.py
wauo/__init__.py
wauo/printer.py
wauo/_test/_go.py
wauo/_test/_printer.py
wauo/_test/do.py
wauo/_test/monitor.py
wauo/_test/nget.py
wauo/_test/pv.py
wauo/_test/raise_for_status.py
wauo/_test/raise_for_text.py
wauo/_test/raise_text.py
wauo/_test/type_check.py
wauo/db/__init__.py
wauo/db/mysql.py
wauo/db/psql.py
wauo/db/test_mysql.py
wauo/db/test_psql.py
wauo/pool/__init__.py
wauo/pool/thread_pool.py
wauo/spiders/__init__.py
wauo/spiders/errors.py
wauo/spiders/response.py
wauo/spiders/spiders.py
wauo/utils/__init__.py
wauo/utils/decors.py
wauo/utils/funcs.py
wauo/utils/loger.py
wauo/utils/pools.py
wauo-0.9.7.dist-info/METADATA
wauo-0.9.7.dist-info/WHEEL
wauo-0.9.7.dist-info/top_level.txt
wauo-0.9.7.dist-info/RECORD
