Metadata-Version: 2.4
Name: wauo
Version: 0.9.7
Summary: A comprehensive Python utility library featuring web scraping, decorators, thread pool management, and database operations
Author-email: WangTuo <markadc@126.com>
License: MIT
Project-URL: Documentation, https://github.com/markadc/wauo#-usage-guide
Project-URL: Homepage, https://github.com/markadc/wauo
Project-URL: Issues, https://github.com/markadc/wauo/issues
Project-URL: Repository, https://github.com/markadc/wauo.git
Keywords: spider,crawler,web-scraping,thread-pool,database,mysql,postgresql,utils,decorators
Classifier: Development Status :: 4 - Beta
Classifier: Environment :: Console
Classifier: Intended Audience :: Developers
Classifier: License :: OSI Approved :: MIT License
Classifier: Natural Language :: Chinese (Simplified)
Classifier: Natural Language :: English
Classifier: Operating System :: OS Independent
Classifier: Programming Language :: Python :: 3
Classifier: Programming Language :: Python :: 3.10
Classifier: Programming Language :: Python :: 3.11
Classifier: Programming Language :: Python :: 3.12
Classifier: Topic :: Internet :: WWW/HTTP
Classifier: Topic :: Software Development :: Libraries :: Python Modules
Classifier: Topic :: Utilities
Requires-Python: >=3.10
Requires-Dist: requests
Requires-Dist: parsel
Requires-Dist: fake_useragent
Requires-Dist: loguru
Requires-Dist: pymysql
Requires-Dist: psycopg2
Requires-Dist: dbutils
